{
    "Master Script Total Time (s)": 75.95100000000001,
    "Cost Information": {
        "615 MB Total Time (s)": 212.41004,
        "615 MB Total Billed Time (s)": 214.098,
        "615 MB Total GB*s": 128.584248046875,
        "615 MB Total Cost (USD)": 0.0021430750869228517,
        "Total Cost": 0.0021430750869228517
    },
    "4d9c38a0-ccc7-4615-b108-4abe5813b714": {
        "date": "Thu, 23 Jun 2022 23:42:15 GMT",
        "status": 202,
        "data": {
            "grouping_to_process": 0,
            "product_type": "latlon",
            "output_freq_code": "AVG_MON",
            "time_steps_to_process": [
                "0000000732",
                "0000001428",
                "0000002172"
            ],
            "dimension": "2D"
        },
        "report": [
            {
                "logStreamName": "2022/06/23/[$LATEST]ce3fdf4ce5e14bd3a5a5d0b2920534db",
                "Duration (s)": 40.446580000000004,
                "Billed Duration (s)": 40.764,
                "Memory Size (MB)": 615,
                "Max Memory Used (MB)": 277,
                "Init Duration (s)": 0.31667,
                "Cost Estimate (USD)": 0.0004080389020136719
            }
        ],
        "error": [],
        "end": true,
        "success": true,
        "extra": {
            "Duration (s)": {
                "TOTAL": 39.74237036705017,
                "SCRIPT": 37.886422872543335,
                "DOWNLOAD": 0.507556676864624,
                "NETCDF": 0.8763113021850586,
                "UPLOAD": 0.4720795154571533
            },
            "Files (#)": {
                "DOWNLOAD": 9,
                "UPLOAD": 3
            }
        }
    },
    "57911755-5a09-449a-a0a0-fa20e2251b14": {
        "date": "Thu, 23 Jun 2022 23:42:17 GMT",
        "status": 202,
        "data": {
            "grouping_to_process": 0,
            "product_type": "latlon",
            "output_freq_code": "AVG_MON",
            "time_steps_to_process": [
                "0000000732",
                "0000001428",
                "0000002172"
            ],
            "dimension": "2D"
        },
        "report": [
            {
                "logStreamName": "2022/06/23/[$LATEST]038155ee499d451dbc5e30488821b637",
                "Duration (s)": 42.82431,
                "Billed Duration (s)": 43.217,
                "Memory Size (MB)": 615,
                "Max Memory Used (MB)": 277,
                "Init Duration (s)": 0.39246,
                "Cost Estimate (USD)": 0.000432592906199707
            }
        ],
        "error": [],
        "end": true,
        "success": true,
        "extra": {
            "Duration (s)": {
                "TOTAL": 41.82216691970825,
                "SCRIPT": 39.8622522354126,
                "DOWNLOAD": 0.4838881492614746,
                "NETCDF": 0.9042091369628906,
                "UPLOAD": 0.5718173980712891
            },
            "Files (#)": {
                "DOWNLOAD": 9,
                "UPLOAD": 3
            }
        }
    },
    "0268f868-5b29-4b7f-ae17-ec06a54c45e1": {
        "date": "Thu, 23 Jun 2022 23:42:18 GMT",
        "status": 202,
        "data": {
            "grouping_to_process": 0,
            "product_type": "latlon",
            "output_freq_code": "AVG_MON",
            "time_steps_to_process": [
                "0000000732",
                "0000001428",
                "0000002172"
            ],
            "dimension": "2D"
        },
        "report": [
            {
                "logStreamName": "2022/06/23/[$LATEST]04b1da9aaed34655ab888dffe6d2d8a4",
                "Duration (s)": 43.458290000000005,
                "Billed Duration (s)": 43.842,
                "Memory Size (MB)": 615,
                "Max Memory Used (MB)": 277,
                "Init Duration (s)": 0.38327999999999995,
                "Cost Estimate (USD)": 0.00043884902222753904
            }
        ],
        "error": [],
        "end": true,
        "success": true,
        "extra": {
            "Duration (s)": {
                "TOTAL": 42.53490138053894,
                "SCRIPT": 40.5744366645813,
                "DOWNLOAD": 0.4864332675933838,
                "NETCDF": 0.9213612079620361,
                "UPLOAD": 0.5526702404022217
            },
            "Files (#)": {
                "DOWNLOAD": 9,
                "UPLOAD": 3
            }
        }
    },
    "323cb422-320c-4d37-aad8-59365cb4ef57": {
        "date": "Thu, 23 Jun 2022 23:42:19 GMT",
        "status": 202,
        "data": {
            "grouping_to_process": 0,
            "product_type": "latlon",
            "output_freq_code": "AVG_MON",
            "time_steps_to_process": [
                "0000000732",
                "0000001428",
                "0000002172"
            ],
            "dimension": "2D"
        },
        "report": [
            {
                "logStreamName": "2022/06/23/[$LATEST]e7d8e44cf9d1451f9a8865ec83c759df",
                "Duration (s)": 42.68096,
                "Billed Duration (s)": 42.995,
                "Memory Size (MB)": 615,
                "Max Memory Used (MB)": 277,
                "Init Duration (s)": 0.31403,
                "Cost Estimate (USD)": 0.0004303707337866211
            }
        ],
        "error": [],
        "end": true,
        "success": true,
        "extra": {
            "Duration (s)": {
                "TOTAL": 41.77109503746033,
                "SCRIPT": 39.852200984954834,
                "DOWNLOAD": 0.4811406135559082,
                "NETCDF": 0.8952891826629639,
                "UPLOAD": 0.5424642562866211
            },
            "Files (#)": {
                "DOWNLOAD": 9,
                "UPLOAD": 3
            }
        }
    },
    "e931615e-707f-4233-9518-fb2be6b825a2": {
        "date": "Thu, 23 Jun 2022 23:42:20 GMT",
        "status": 202,
        "data": {
            "grouping_to_process": 0,
            "product_type": "latlon",
            "output_freq_code": "AVG_MON",
            "time_steps_to_process": [
                "0000000732",
                "0000001428",
                "0000002172"
            ],
            "dimension": "2D"
        },
        "report": [
            {
                "logStreamName": "2022/06/23/[$LATEST]2467a0ea806f4fd89a73620883056b3c",
                "Duration (s)": 42.999900000000004,
                "Billed Duration (s)": 43.28,
                "Memory Size (MB)": 615,
                "Max Memory Used (MB)": 280,
                "Init Duration (s)": 0.27922,
                "Cost Estimate (USD)": 0.00043322352269531254
            }
        ],
        "error": [],
        "end": true,
        "success": true,
        "extra": {
            "Duration (s)": {
                "TOTAL": 42.14970850944519,
                "SCRIPT": 40.216559648513794,
                "DOWNLOAD": 0.47347426414489746,
                "NETCDF": 0.9102933406829834,
                "UPLOAD": 0.5493812561035156
            },
            "Files (#)": {
                "DOWNLOAD": 9,
                "UPLOAD": 3
            }
        }
    }
}